braise/__init__.py
braise/lunch_spider.py
braise-0.5.data/scripts/lunch
braise-0.5.data/scripts/menu
braise-0.5.dist-info/DESCRIPTION.rst
braise-0.5.dist-info/METADATA
braise-0.5.dist-info/RECORD
braise-0.5.dist-info/WHEEL
braise-0.5.dist-info/metadata.json
braise-0.5.dist-info/top_level.txt
lunchboy/__init__.py
lunchboy/lunch_spider.py
