Metadata-Version: 2.0
Name: braise
Version: 0.5
Summary: Lunch without #lunch
Home-page: http://github.com/lisunshiny/braise
Author: Liann Sun
Author-email: liann@braze.com
License: MIT
Platform: UNKNOWN
Requires-Dist: Scrapy
